llm_mlc.py
llm_mlc-0.5.dist-info/LICENSE
llm_mlc-0.5.dist-info/METADATA
llm_mlc-0.5.dist-info/WHEEL
llm_mlc-0.5.dist-info/entry_points.txt
llm_mlc-0.5.dist-info/top_level.txt
llm_mlc-0.5.dist-info/RECORD
