Metadata-Version: 2.1
Name: llm-mlc
Version: 0.5
Summary: LLM plugin for running models using MLC
Author: Simon Willison
License: Apache-2.0
Project-URL: Homepage, https://github.com/simonw/llm-mlc
Project-URL: Changelog, https://github.com/simonw/llm-mlc/releases
Project-URL: Issues, https://github.com/simonw/llm-mlc/issues
Project-URL: CI, https://github.com/simonw/llm-mlc/actions
Classifier: License :: OSI Approved :: Apache Software License
License-File: LICENSE
Requires-Dist: llm >=0.7
Requires-Dist: httpx
Provides-Extra: test
Requires-Dist: pytest ; extra == 'test'
